{
  "$schema": "https://developer.microsoft.com/json-schemas/fabric/item/report/definition/page/2.0.0/schema.json",
  "name": "bfdc9b7218c310d6daac",
  "displayName": "Day 5 Part 1",
  "displayOption": "FitToPage",
  "height": 720,
  "width": 1280,
  "objects": {
    "outspacePane": [
      {
        "properties": {
          "width": {
            "expr": {
              "Literal": {
                "Value": "304L"
              }
            }
          }
        }
      }
    ],
    "background": [
      {
        "properties": {
          "color": {
            "solid": {
              "color": {
                "expr": {
                  "ThemeDataColor": {
                    "ColorId": 0,
                    "Percent": -0.2
                  }
                }
              }
            }
          },
          "transparency": {
            "expr": {
              "Literal": {
                "Value": "84D"
              }
            }
          }
        }
      }
    ]
  },
  "visualInteractions": [
    {
      "source": "30beb396dc6e5d6c1245",
      "target": "6b2ef2ca58b7ca61ae04",
      "type": "NoFilter"
    }
  ]
}